fakeitmakeit/__init__.py
fakeitmakeit/factory.py
fakeitmakeit/isvalid.py
fakeitmakeit/util.py
fakeitmakeit-2025.10.0.dist-info/METADATA
fakeitmakeit-2025.10.0.dist-info/WHEEL
fakeitmakeit-2025.10.0.dist-info/licenses/LICENSE
fakeitmakeit-2025.10.0.dist-info/RECORD
