Metadata-Version: 2.4
Name: fakeitmakeit
Version: 2025.10.0
Summary: Python package for generating fake student data.
Author-email: Marijan Beg <m.beg@imperial.ac.uk>
License-Expression: MIT
License-File: LICENSE
Keywords: fake,synthetic-data,testing
Classifier: Development Status :: 5 - Production/Stable
Classifier: Intended Audience :: Developers
Classifier: Intended Audience :: Education
Classifier: License :: OSI Approved :: MIT License
Classifier: Natural Language :: English
Classifier: Operating System :: OS Independent
Requires-Python: >=3.13
Requires-Dist: faker>=30.8.0
Requires-Dist: pandas>=2.2.3
Requires-Dist: pycountry>=24.6.1
